ngtk/__init__.py
ngtk/cli.py
ngtk-0.1.1.dist-info/DESCRIPTION.rst
ngtk-0.1.1.dist-info/METADATA
ngtk-0.1.1.dist-info/RECORD
ngtk-0.1.1.dist-info/WHEEL
ngtk-0.1.1.dist-info/entry_points.txt
ngtk-0.1.1.dist-info/metadata.json
ngtk-0.1.1.dist-info/top_level.txt
