Metadata-Version: 2.0
Name: ngtk
Version: 0.1.1
Summary: A command line toolkit for ngrok.
Home-page: https://github.com/Jigsaw-Jams/ngtk
Author: DJ Strasser
Author-email: test_test_test_test@gmail.com
License: UNKNOWN
Platform: UNKNOWN
Requires-Dist: Click
Requires-Dist: requests
Requires-Dist: crayons
